markdown_pdf/__init__.py
markdown_pdf/py.typed
markdown_pdf-1.9.dist-info/LICENSE
markdown_pdf-1.9.dist-info/METADATA
markdown_pdf-1.9.dist-info/WHEEL
markdown_pdf-1.9.dist-info/top_level.txt
markdown_pdf-1.9.dist-info/RECORD
