Metadata-Version: 2.1
Name: markdown_pdf
Version: 1.9
Summary: Markdown to pdf renderer
Author-email: Vitaly Bogomolov <mail@vitaly-bogomolov.ru>
License: GNU Affero General Public License v3
Project-URL: Homepage, https://github.com/vb64/markdown-pdf
Project-URL: Bug Tracker, https://github.com/vb64/markdown-pdf/issues
Classifier: Programming Language :: Python :: 3
Classifier: License :: OSI Approved :: GNU Affero General Public License v3
Classifier: Operating System :: OS Independent
Requires-Python: >=3.8
License-File: LICENSE
Requires-Dist: PyMuPDF==1.24.6; python_version < "3.9"
Requires-Dist: PyMuPDF>=1.25.3; python_version > "3.8"
Requires-Dist: markdown-it-py==3.0.0; python_version >= "3.8"
Provides-Extra: dev
Requires-Dist: flake8; extra == "dev"
Requires-Dist: pylint; extra == "dev"
Requires-Dist: pydocstyle; extra == "dev"
Requires-Dist: pytest; extra == "dev"
Requires-Dist: pytest-cov; extra == "dev"
Requires-Dist: codacy-coverage; extra == "dev"
